{"type": "Feature", "properties": {"citycode": "0518", "adcode": "320723", "name": "灌云县", "center": [119.239426, 34.284074], "centroid": [], "childrenNum": 15, "level": "district", "acroutes": ["100000", "320000", "320700", "320723"], "districts": [{"type": "Feature", "properties": {"citycode": "0518", "adcode": "320723", "name": "小伊镇", "center": [119.222694, 34.362437], "centroid": [], "childrenNum": 0, "level": "street", "acroutes": ["100000", "320000", "320700", "320723"], "districts": []}, "geometry": {"type": "MultiPolygon", "coordinates": []}}, {"type": "Feature", "properties": {"citycode": "0518", "adcode": "320723", "name": "东王集镇", "center": [119.350328, 34.298074], "centroid": [], "childrenNum": 0, "level": "street", "acroutes": ["100000", "320000", "320700", "320723"], "districts": []}, "geometry": {"type": "MultiPolygon", "coordinates": []}}, {"type": "Feature", "properties": {"citycode": "0518", "adcode": "320723", "name": "下车镇", "center": [119.305661, 34.419304], "centroid": [], "childrenNum": 0, "level": "street", "acroutes": ["100000", "320000", "320700", "320723"], "districts": []}, "geometry": {"type": "MultiPolygon", "coordinates": []}}, {"type": "Feature", "properties": {"citycode": "0518", "adcode": "320723", "name": "侍庄街道", "center": [119.269571, 34.216503], "centroid": [], "childrenNum": 0, "level": "street", "acroutes": ["100000", "320000", "320700", "320723"], "districts": []}, "geometry": {"type": "MultiPolygon", "coordinates": []}}, {"type": "Feature", "properties": {"citycode": "0518", "adcode": "320723", "name": "四队镇", "center": [119.461359, 34.484242], "centroid": [], "childrenNum": 0, "level": "street", "acroutes": ["100000", "320000", "320700", "320723"], "districts": []}, "geometry": {"type": "MultiPolygon", "coordinates": []}}, {"type": "Feature", "properties": {"citycode": "0518", "adcode": "320723", "name": "同兴镇", "center": [119.253569, 34.452176], "centroid": [], "childrenNum": 0, "level": "street", "acroutes": ["100000", "320000", "320700", "320723"], "districts": []}, "geometry": {"type": "MultiPolygon", "coordinates": []}}, {"type": "Feature", "properties": {"citycode": "0518", "adcode": "320723", "name": "杨集镇", "center": [119.500417, 34.367327], "centroid": [], "childrenNum": 0, "level": "street", "acroutes": ["100000", "320000", "320700", "320723"], "districts": []}, "geometry": {"type": "MultiPolygon", "coordinates": []}}, {"type": "Feature", "properties": {"citycode": "0518", "adcode": "320723", "name": "龙苴镇", "center": [119.059864, 34.430104], "centroid": [], "childrenNum": 0, "level": "street", "acroutes": ["100000", "320000", "320700", "320723"], "districts": []}, "geometry": {"type": "MultiPolygon", "coordinates": []}}, {"type": "Feature", "properties": {"citycode": "0518", "adcode": "320723", "name": "南岗镇", "center": [119.076428, 34.284843], "centroid": [], "childrenNum": 0, "level": "street", "acroutes": ["100000", "320000", "320700", "320723"], "districts": []}, "geometry": {"type": "MultiPolygon", "coordinates": []}}, {"type": "Feature", "properties": {"citycode": "0518", "adcode": "320723", "name": "伊山镇", "center": [119.186534, 34.360527], "centroid": [], "childrenNum": 0, "level": "street", "acroutes": ["100000", "320000", "320700", "320723"], "districts": []}, "geometry": {"type": "MultiPolygon", "coordinates": []}}, {"type": "Feature", "properties": {"citycode": "0518", "adcode": "320723", "name": "圩丰镇", "center": [119.595656, 34.4889], "centroid": [], "childrenNum": 0, "level": "street", "acroutes": ["100000", "320000", "320700", "320723"], "districts": []}, "geometry": {"type": "MultiPolygon", "coordinates": []}}, {"type": "Feature", "properties": {"citycode": "0518", "adcode": "320723", "name": "五图河农场", "center": [119.668656, 34.36925], "centroid": [], "childrenNum": 0, "level": "street", "acroutes": ["100000", "320000", "320700", "320723"], "districts": []}, "geometry": {"type": "MultiPolygon", "coordinates": []}}, {"type": "Feature", "properties": {"citycode": "0518", "adcode": "320723", "name": "燕尾港镇", "center": [119.739493, 34.43262], "centroid": [], "childrenNum": 0, "level": "street", "acroutes": ["100000", "320000", "320700", "320723"], "districts": []}, "geometry": {"type": "MultiPolygon", "coordinates": []}}, {"type": "Feature", "properties": {"citycode": "0518", "adcode": "320723", "name": "灌西盐场", "center": [119.625791, 34.501068], "centroid": [], "childrenNum": 0, "level": "street", "acroutes": ["100000", "320000", "320700", "320723"], "districts": []}, "geometry": {"type": "MultiPolygon", "coordinates": []}}, {"type": "Feature", "properties": {"citycode": "0518", "adcode": "320723", "name": "图河镇", "center": [119.656145, 34.354259], "centroid": [], "childrenNum": 0, "level": "street", "acroutes": ["100000", "320000", "320700", "320723"], "districts": []}, "geometry": {"type": "MultiPolygon", "coordinates": []}}]}, "geometry": {"type": "MultiPolygon", "coordinates": [[[[119.075544, 34.439959], [119.064371, 34.439513], [119.064284, 34.439281], [119.060759, 34.42919], [119.060751, 34.42874], [119.061216, 34.42017], [119.071805, 34.420713], [119.089541, 34.420866], [119.089395, 34.420253], [119.086887, 34.409767], [119.065273, 34.409248], [119.065044, 34.40845], [119.064811, 34.396842], [119.064391, 34.396882], [119.06253, 34.396912], [119.060551, 34.393991], [119.058105, 34.389596], [119.057783, 34.388591], [119.054815, 34.376082], [119.054493, 34.372399], [119.056777, 34.351743], [119.054491, 34.351708], [119.054591, 34.349527], [119.054691, 34.349447], [119.057759, 34.349734], [119.058561, 34.346764], [119.060205, 34.346067], [119.062419, 34.346641], [119.064855, 34.347066], [119.065556, 34.343375], [119.067831, 34.344939], [119.067991, 34.344349], [119.068243, 34.337493], [119.068391, 34.337456], [119.075825, 34.342219], [119.074212, 34.336004], [119.073139, 34.3313], [119.07337, 34.32962], [119.074721, 34.324699], [119.074972, 34.324079], [119.081531, 34.317244], [119.081991, 34.316464], [119.082752, 34.311732], [119.082711, 34.311302], [119.080837, 34.300885], [119.079405, 34.301094], [119.077032, 34.301051], [119.076261, 34.297979], [119.071692, 34.298523], [119.071632, 34.294171], [119.073675, 34.28625], [119.076399, 34.286424], [119.077371, 34.287546], [119.07713, 34.286365], [119.071509, 34.267589], [119.071629, 34.267219], [119.079511, 34.263868], [119.079898, 34.263832], [119.090723, 34.262286], [119.09056, 34.261137], [119.092784, 34.259026], [119.092494, 34.256945], [119.094395, 34.252704], [119.094273, 34.251879], [119.091553, 34.250432], [119.091577, 34.248309], [119.091251, 34.240218], [119.092462, 34.240179], [119.097172, 34.229751], [119.097087, 34.228793], [119.098551, 34.204377], [119.103282, 34.203618], [119.11366, 34.201955], [119.113722, 34.204067], [119.11384, 34.206227], [119.123763, 34.20588], [119.131165, 34.205813], [119.131255, 34.205643], [119.133122, 34.198769], [119.133981, 34.198597], [119.138105, 34.199583], [119.138843, 34.196941], [119.140441, 34.197419], [119.150802, 34.198154], [119.150842, 34.195362], [119.152389, 34.19533], [119.152502, 34.197247], [119.160134, 34.198868], [119.159954, 34.195367], [119.162809, 34.195754], [119.162938, 34.199103], [119.178933, 34.199063], [119.180589, 34.201861], [119.180669, 34.201891], [119.183871, 34.201144], [119.213561, 34.203465], [119.21344, 34.200794], [119.215606, 34.200772], [119.215727, 34.203632], [119.223834, 34.204372], [119.223814, 34.201761], [119.224483, 34.204372], [119.224983, 34.204341], [119.225023, 34.20175], [119.226351, 34.201799], [119.228349, 34.203578], [119.231176, 34.203364], [119.231784, 34.201954], [119.231924, 34.204994], [119.244085, 34.207678], [119.244285, 34.207037], [119.244605, 34.205357], [119.247273, 34.205703], [119.247254, 34.208437], [119.264914, 34.21539], [119.265744, 34.21563], [119.294102, 34.222768], [119.295203, 34.219138], [119.295844, 34.216588], [119.297306, 34.216851], [119.296796, 34.2188], [119.298458, 34.219093], [119.297818, 34.222683], [119.296105, 34.223291], [119.298689, 34.223945], [119.30249, 34.224484], [119.313536, 34.22604], [119.314017, 34.226], [119.318967, 34.224419], [119.319758, 34.22443], [119.329749, 34.225129], [119.331874, 34.225521], [119.378408, 34.233603], [119.378818, 34.233554], [119.39553, 34.230226], [119.395481, 34.231417], [119.396951, 34.234169], [119.398406, 34.234447], [119.403735, 34.235537], [119.404081, 34.231704], [119.418155, 34.233789], [119.419334, 34.234308], [119.427815, 34.238904], [119.428354, 34.239014], [119.451298, 34.240802], [119.450989, 34.241913], [119.453901, 34.243148], [119.45404, 34.243147], [119.456154, 34.240192], [119.465824, 34.23902], [119.47163, 34.239766], [119.473294, 34.240108], [119.47354, 34.251506], [119.475443, 34.252051], [119.49206, 34.257196], [119.49216, 34.257366], [119.491035, 34.261921], [119.492509, 34.262487], [119.503725, 34.266596], [119.504932, 34.2674], [119.504421, 34.269574], [119.509405, 34.270729], [119.523525, 34.273929], [119.524034, 34.274118], [119.523545, 34.275319], [119.52751, 34.276349], [119.530524, 34.277999], [119.530419, 34.278161], [119.530051, 34.282354], [119.542634, 34.289861], [119.553002, 34.296064], [119.552414, 34.298066], [119.556542, 34.298847], [119.55706, 34.297015], [119.561737, 34.297303], [119.561946, 34.297316], [119.561867, 34.298197], [119.566854, 34.300679], [119.566894, 34.300869], [119.565039, 34.302113], [119.566036, 34.303198], [119.575176, 34.311573], [119.576274, 34.312312], [119.592899, 34.320722], [119.592949, 34.320912], [119.59284, 34.322338], [119.597106, 34.324072], [119.613879, 34.333399], [119.62014, 34.335423], [119.638442, 34.341445], [119.637595, 34.344477], [119.63582, 34.348325], [119.637448, 34.34921], [119.642958, 34.352087], [119.643959, 34.351958], [119.64522, 34.35053], [119.647498, 34.351613], [119.654232, 34.353385], [119.655153, 34.353898], [119.662886, 34.359224], [119.663286, 34.360155], [119.663647, 34.363177], [119.663787, 34.363327], [119.666902, 34.365214], [119.66509, 34.366472], [119.666501, 34.367733], [119.669394, 34.370012], [119.676731, 34.37032], [119.693505, 34.369987], [119.69707, 34.372625], [119.698664, 34.370876], [119.703557, 34.366031], [119.706161, 34.368097], [119.765525, 34.412661], [119.764577, 34.413965], [119.758239, 34.419529], [119.759987, 34.42094], [119.781202, 34.437092], [119.782695, 34.437747], [119.79659, 34.445382], [119.796923, 34.446315], [119.795567, 34.45049], [119.798604, 34.451117], [119.800375, 34.452634], [119.802459, 34.45182], [119.808612, 34.450069], [119.808837, 34.45048], [119.811834, 34.462302], [119.812083, 34.462492], [119.819212, 34.462859], [119.819941, 34.46634], [119.822995, 34.481984], [119.820846, 34.482113], [119.811597, 34.485543], [119.785988, 34.512233], [119.781796, 34.51574], [119.741077, 34.532853], [119.679762, 34.553515], [119.641014, 34.508001], [119.622657, 34.499337], [119.621029, 34.497636], [119.615208, 34.490437], [119.61369, 34.490602], [119.608528, 34.495516], [119.607242, 34.496001], [119.605519, 34.495758], [119.603772, 34.494689], [119.591924, 34.487174], [119.590639, 34.487028], [119.563963, 34.491326], [119.562416, 34.490965], [119.553734, 34.488625], [119.551511, 34.489233], [119.536264, 34.499481], [119.533634, 34.500107], [119.530856, 34.500126], [119.528804, 34.499544], [119.519543, 34.493866], [119.516653, 34.493252], [119.475592, 34.487839], [119.471653, 34.486646], [119.412078, 34.468764], [119.410808, 34.468647], [119.40426, 34.468657], [119.403546, 34.47047], [119.401118, 34.471781], [119.400975, 34.471367], [119.400345, 34.468662], [119.384878, 34.468704], [119.256943, 34.462922], [119.250947, 34.460771], [119.243974, 34.458276], [119.235427, 34.458337], [119.234593, 34.460513], [119.224531, 34.459552], [119.220491, 34.459203], [119.219865, 34.45896], [119.212772, 34.453739], [119.214488, 34.451355], [119.216046, 34.448102], [119.213752, 34.447174], [119.210698, 34.446922], [119.208064, 34.450536], [119.205295, 34.448518], [119.191695, 34.435435], [119.169892, 34.437263], [119.160313, 34.438413], [119.160202, 34.436862], [119.162609, 34.436442], [119.162607, 34.433345], [119.162187, 34.428543], [119.158874, 34.428309], [119.157956, 34.433084], [119.15612, 34.433537], [119.155013, 34.435981], [119.154843, 34.43485], [119.155941, 34.431296], [119.149513, 34.430856], [119.135926, 34.429455], [119.135516, 34.427154], [119.134577, 34.427115], [119.134587, 34.427345], [119.135057, 34.432457], [119.132277, 34.432963], [119.131393, 34.433893], [119.130234, 34.433974], [119.129993, 34.431312], [119.129131, 34.43141], [119.117496, 34.432814], [119.118134, 34.436258], [119.114168, 34.438059], [119.114679, 34.442411], [119.112269, 34.443193], [119.10034, 34.446966], [119.10016, 34.441233], [119.094508, 34.441661], [119.094768, 34.442792], [119.091705, 34.443141], [119.092547, 34.446854], [119.092625, 34.448079], [119.088037, 34.446399], [119.07639, 34.440122], [119.075544, 34.439959]]]]}}