{"type": "Feature", "properties": {"citycode": "0895", "adcode": "540324", "name": "丁青县", "center": [95.619868, 31.409024], "centroid": [], "childrenNum": 13, "level": "district", "acroutes": ["100000", "540000", "540300", "540324"], "districts": [{"type": "Feature", "properties": {"citycode": "0895", "adcode": "540324", "name": "木塔乡", "center": [95.043824, 32.401081], "centroid": [], "childrenNum": 0, "level": "street", "acroutes": ["100000", "540000", "540300", "540324"], "districts": []}, "geometry": {"type": "MultiPolygon", "coordinates": []}}, {"type": "Feature", "properties": {"citycode": "0895", "adcode": "540324", "name": "沙贡乡", "center": [95.687113, 31.260863], "centroid": [], "childrenNum": 0, "level": "street", "acroutes": ["100000", "540000", "540300", "540324"], "districts": []}, "geometry": {"type": "MultiPolygon", "coordinates": []}}, {"type": "Feature", "properties": {"citycode": "0895", "adcode": "540324", "name": "甘岩乡", "center": [95.061653, 31.919118], "centroid": [], "childrenNum": 0, "level": "street", "acroutes": ["100000", "540000", "540300", "540324"], "districts": []}, "geometry": {"type": "MultiPolygon", "coordinates": []}}, {"type": "Feature", "properties": {"citycode": "0895", "adcode": "540324", "name": "协雄乡", "center": [95.622198, 31.421482], "centroid": [], "childrenNum": 0, "level": "street", "acroutes": ["100000", "540000", "540300", "540324"], "districts": []}, "geometry": {"type": "MultiPolygon", "coordinates": []}}, {"type": "Feature", "properties": {"citycode": "0895", "adcode": "540324", "name": "尺犊镇", "center": [94.855834, 31.605327], "centroid": [], "childrenNum": 0, "level": "street", "acroutes": ["100000", "540000", "540300", "540324"], "districts": []}, "geometry": {"type": "MultiPolygon", "coordinates": []}}, {"type": "Feature", "properties": {"citycode": "0895", "adcode": "540324", "name": "色扎乡", "center": [95.19839, 31.647128], "centroid": [], "childrenNum": 0, "level": "street", "acroutes": ["100000", "540000", "540300", "540324"], "districts": []}, "geometry": {"type": "MultiPolygon", "coordinates": []}}, {"type": "Feature", "properties": {"citycode": "0895", "adcode": "540324", "name": "布塔乡", "center": [95.241023, 32.281511], "centroid": [], "childrenNum": 0, "level": "street", "acroutes": ["100000", "540000", "540300", "540324"], "districts": []}, "geometry": {"type": "MultiPolygon", "coordinates": []}}, {"type": "Feature", "properties": {"citycode": "0895", "adcode": "540324", "name": "丁青镇", "center": [95.724297, 31.763522], "centroid": [], "childrenNum": 0, "level": "street", "acroutes": ["100000", "540000", "540300", "540324"], "districts": []}, "geometry": {"type": "MultiPolygon", "coordinates": []}}, {"type": "Feature", "properties": {"citycode": "0895", "adcode": "540324", "name": "觉恩乡", "center": [96.211966, 31.031807], "centroid": [], "childrenNum": 0, "level": "street", "acroutes": ["100000", "540000", "540300", "540324"], "districts": []}, "geometry": {"type": "MultiPolygon", "coordinates": []}}, {"type": "Feature", "properties": {"citycode": "0895", "adcode": "540324", "name": "嘎塔乡", "center": [94.688492, 32.038023], "centroid": [], "childrenNum": 0, "level": "street", "acroutes": ["100000", "540000", "540300", "540324"], "districts": []}, "geometry": {"type": "MultiPolygon", "coordinates": []}}, {"type": "Feature", "properties": {"citycode": "0895", "adcode": "540324", "name": "桑多乡", "center": [95.825479, 31.12991], "centroid": [], "childrenNum": 0, "level": "street", "acroutes": ["100000", "540000", "540300", "540324"], "districts": []}, "geometry": {"type": "MultiPolygon", "coordinates": []}}, {"type": "Feature", "properties": {"citycode": "0895", "adcode": "540324", "name": "巴达乡", "center": [94.760677, 31.577305], "centroid": [], "childrenNum": 0, "level": "street", "acroutes": ["100000", "540000", "540300", "540324"], "districts": []}, "geometry": {"type": "MultiPolygon", "coordinates": []}}, {"type": "Feature", "properties": {"citycode": "0895", "adcode": "540324", "name": "当堆乡", "center": [95.293085, 31.156266], "centroid": [], "childrenNum": 0, "level": "street", "acroutes": ["100000", "540000", "540300", "540324"], "districts": []}, "geometry": {"type": "MultiPolygon", "coordinates": []}}]}, "geometry": {"type": "MultiPolygon", "coordinates": [[[[95.023551, 32.40933], [95.013785, 32.40943], [95.012975, 32.409753], [94.986969, 32.422747], [94.986019, 32.422701], [94.9875, 32.417062], [94.987047, 32.416514], [94.980426, 32.409326], [94.980086, 32.409176], [94.968659, 32.407172], [94.968058, 32.407116], [94.952553, 32.412134], [94.952031, 32.412004], [94.941728, 32.403775], [94.941545, 32.403853], [94.938431, 32.408433], [94.938057, 32.408502], [94.918705, 32.411236], [94.91523, 32.413439], [94.903239, 32.443175], [94.902812, 32.445406], [94.903452, 32.453144], [94.901263, 32.455593], [94.891743, 32.471372], [94.889913, 32.472338], [94.852126, 32.463576], [94.850763, 32.464599], [94.84206, 32.475879], [94.832368, 32.480039], [94.827662, 32.478641], [94.826101, 32.47937], [94.815481, 32.487424], [94.812648, 32.487975], [94.806801, 32.486329], [94.80514, 32.48953], [94.795369, 32.498901], [94.795346, 32.500624], [94.794493, 32.513965], [94.792116, 32.51503], [94.785778, 32.524434], [94.781793, 32.524631], [94.759434, 32.529367], [94.757811, 32.5272], [94.740715, 32.516493], [94.74074, 32.515251], [94.738923, 32.491926], [94.738142, 32.491992], [94.723508, 32.50167], [94.720226, 32.502153], [94.714352, 32.501729], [94.71069, 32.49943], [94.697064, 32.467446], [94.695879, 32.467225], [94.649636, 32.460651], [94.650023, 32.460398], [94.685159, 32.446167], [94.685822, 32.444988], [94.684613, 32.433486], [94.685888, 32.431927], [94.690915, 32.423705], [94.690613, 32.421447], [94.684963, 32.410259], [94.685443, 32.408075], [94.689368, 32.401908], [94.691655, 32.399647], [94.721334, 32.365257], [94.730026, 32.360458], [94.746662, 32.344766], [94.747604, 32.344698], [94.761095, 32.340193], [94.760839, 32.339549], [94.758282, 32.324032], [94.755593, 32.317644], [94.747285, 32.304454], [94.747278, 32.304109], [94.742684, 32.260119], [94.738985, 32.257686], [94.722476, 32.246236], [94.721658, 32.245915], [94.703587, 32.240731], [94.701969, 32.239399], [94.668476, 32.211919], [94.668562, 32.207754], [94.663253, 32.194744], [94.666228, 32.192091], [94.673825, 32.189826], [94.673453, 32.189031], [94.656721, 32.180451], [94.656081, 32.179217], [94.658304, 32.158484], [94.656871, 32.156515], [94.650373, 32.152866], [94.649833, 32.151713], [94.648713, 32.141882], [94.649807, 32.135887], [94.646076, 32.100028], [94.646787, 32.098062], [94.664464, 32.082836], [94.663764, 32.067378], [94.660713, 32.054825], [94.661514, 32.054265], [94.691113, 32.043714], [94.691064, 32.042778], [94.664305, 31.997607], [94.662791, 31.996245], [94.64536, 31.989326], [94.64961, 31.987489], [94.664859, 31.978049], [94.664851, 31.977565], [94.661023, 31.970525], [94.664911, 31.959949], [94.671828, 31.953241], [94.674351, 31.941992], [94.67522, 31.928469], [94.676247, 31.908298], [94.673097, 31.897565], [94.647495, 31.883383], [94.647399, 31.877427], [94.649251, 31.840754], [94.653722, 31.833611], [94.752931, 31.797962], [94.757158, 31.792867], [94.773459, 31.723004], [94.770649, 31.715481], [94.755716, 31.706967], [94.747122, 31.707756], [94.738498, 31.707174], [94.730827, 31.698785], [94.723606, 31.685347], [94.714409, 31.682699], [94.686586, 31.678171], [94.682933, 31.669274], [94.684872, 31.638779], [94.698842, 31.636575], [94.715173, 31.647401], [94.72888, 31.645875], [94.751366, 31.639878], [94.755012, 31.632957], [94.763389, 31.61548], [94.762817, 31.615121], [94.752931, 31.607561], [94.753549, 31.604406], [94.754609, 31.591727], [94.756555, 31.586716], [94.768093, 31.562127], [94.771326, 31.560899], [94.847043, 31.555571], [94.859304, 31.55149], [94.892307, 31.536806], [94.898043, 31.527329], [94.905335, 31.500182], [94.912396, 31.489773], [94.911935, 31.479693], [94.90853, 31.469423], [94.879562, 31.439792], [94.874584, 31.431382], [94.871038, 31.413093], [94.879978, 31.403563], [94.886527, 31.394988], [94.895273, 31.389822], [94.926019, 31.369689], [94.930748, 31.378571], [94.947674, 31.378596], [94.953514, 31.374857], [94.973094, 31.358352], [94.977005, 31.352118], [94.977248, 31.336065], [94.985219, 31.33139], [94.992963, 31.314333], [94.989548, 31.304512], [94.982857, 31.291973], [94.988684, 31.287553], [94.989005, 31.286518], [94.997389, 31.285286], [95.014273, 31.290287], [95.018601, 31.289499], [95.047486, 31.282996], [95.049459, 31.282046], [95.059018, 31.277858], [95.062191, 31.272062], [95.068074, 31.262084], [95.070339, 31.261398], [95.078754, 31.263881], [95.080961, 31.260586], [95.077751, 31.252809], [95.080718, 31.249502], [95.087039, 31.225928], [95.103339, 31.208055], [95.103224, 31.202839], [95.115191, 31.195463], [95.11932, 31.193078], [95.122489, 31.192924], [95.165622, 31.183892], [95.177374, 31.183502], [95.214786, 31.184452], [95.228606, 31.181007], [95.24377, 31.177543], [95.25435, 31.171636], [95.271876, 31.15393], [95.273526, 31.143373], [95.276941, 31.145219], [95.285945, 31.153115], [95.293039, 31.156227], [95.301751, 31.157508], [95.309587, 31.152185], [95.317389, 31.142341], [95.333168, 31.140739], [95.347146, 31.134624], [95.355042, 31.134573], [95.383267, 31.140987], [95.384184, 31.139972], [95.387375, 31.126768], [95.386978, 31.125469], [95.382504, 31.1187], [95.384665, 31.118077], [95.395824, 31.121347], [95.397724, 31.121234], [95.403881, 31.117731], [95.40414, 31.116093], [95.390429, 31.110968], [95.389833, 31.10984], [95.392314, 31.104027], [95.393886, 31.10318], [95.401821, 31.104132], [95.404582, 31.106162], [95.414556, 31.114274], [95.416195, 31.113877], [95.442208, 31.099032], [95.443312, 31.097279], [95.455876, 31.073877], [95.457305, 31.072744], [95.463246, 31.068659], [95.464478, 31.06527], [95.474455, 31.035943], [95.475169, 31.034586], [95.481426, 31.029933], [95.482322, 31.026036], [95.476698, 31.020135], [95.476956, 31.018894], [95.487902, 31.013202], [95.488092, 31.012298], [95.483843, 31.007206], [95.485097, 31.006745], [95.501894, 31.010946], [95.512192, 31.018756], [95.533408, 31.037348], [95.535822, 31.048767], [95.545565, 31.054988], [95.573067, 31.078287], [95.588453, 31.084869], [95.600415, 31.093572], [95.603435, 31.101947], [95.603817, 31.1222], [95.607788, 31.127094], [95.615119, 31.129745], [95.616699, 31.131999], [95.630488, 31.14765], [95.633256, 31.148306], [95.64351, 31.121372], [95.644693, 31.12298], [95.655473, 31.128646], [95.664538, 31.127172], [95.686512, 31.125402], [95.689462, 31.124439], [95.704089, 31.117046], [95.707888, 31.117297], [95.713251, 31.132518], [95.711134, 31.138103], [95.702425, 31.151968], [95.7046, 31.152544], [95.770564, 31.153316], [95.786385, 31.151027], [95.815001, 31.141946], [95.82543, 31.129867], [95.84068, 31.112432], [95.856426, 31.110058], [95.883371, 31.107834], [95.893946, 31.103179], [95.9083, 31.099655], [95.913975, 31.089843], [95.940515, 31.053186], [95.950607, 31.047358], [95.965009, 31.044661], [95.971551, 31.035255], [95.993655, 31.003634], [96.003577, 31.003497], [96.022829, 31.004401], [96.025231, 31.010366], [96.038133, 31.023604], [96.048769, 31.026818], [96.077349, 31.031923], [96.08643, 31.029398], [96.091984, 31.02296], [96.101266, 31.015818], [96.111098, 31.012329], [96.152939, 31.000696], [96.156294, 30.997768], [96.148459, 30.972693], [96.149509, 30.969667], [96.15885, 30.957117], [96.16242, 30.955527], [96.169597, 30.956502], [96.172905, 30.958369], [96.171858, 30.972198], [96.176424, 30.980322], [96.190929, 31.001296], [96.190924, 31.002999], [96.184297, 31.00906], [96.184335, 31.009742], [96.188933, 31.024107], [96.189615, 31.024671], [96.215451, 31.030144], [96.211914, 31.031763], [96.184573, 31.044271], [96.184232, 31.044735], [96.180514, 31.0594], [96.180815, 31.060302], [96.183989, 31.066172], [96.183081, 31.066836], [96.165534, 31.074622], [96.16522, 31.075212], [96.166126, 31.077958], [96.168744, 31.079545], [96.179356, 31.084447], [96.180024, 31.085227], [96.193026, 31.106233], [96.195635, 31.105089], [96.237808, 31.094283], [96.239607, 31.093198], [96.243929, 31.085348], [96.247426, 31.083497], [96.266262, 31.077317], [96.268412, 31.078561], [96.28644, 31.096821], [96.287107, 31.098391], [96.290459, 31.112534], [96.29117, 31.113004], [96.323531, 31.135648], [96.324929, 31.13576], [96.353738, 31.133961], [96.357365, 31.137812], [96.361831, 31.141681], [96.363058, 31.141754], [96.374864, 31.140675], [96.376197, 31.141998], [96.372246, 31.1493], [96.372338, 31.150203], [96.376806, 31.157056], [96.376091, 31.157641], [96.368898, 31.160889], [96.368116, 31.161773], [96.366073, 31.168236], [96.365602, 31.168426], [96.332139, 31.180061], [96.335081, 31.182924], [96.343311, 31.199616], [96.343403, 31.200823], [96.342398, 31.20653], [96.339299, 31.206777], [96.284378, 31.215586], [96.281651, 31.21671], [96.272497, 31.228915], [96.268564, 31.229053], [96.253653, 31.222252], [96.250391, 31.224155], [96.244458, 31.231868], [96.235397, 31.23414], [96.20098, 31.247163], [96.1995, 31.248316], [96.196149, 31.255636], [96.192028, 31.257471], [96.166114, 31.268456], [96.155182, 31.270547], [96.125324, 31.274556], [96.121876, 31.278146], [96.118679, 31.289084], [96.114155, 31.290611], [96.110402, 31.289949], [96.100447, 31.281964], [96.100074, 31.285677], [96.110944, 31.3195], [96.110381, 31.321717], [96.095777, 31.34093], [96.096013, 31.342033], [96.096616, 31.345259], [96.097546, 31.347063], [96.100648, 31.352544], [96.102257, 31.352305], [96.127348, 31.355463], [96.12236, 31.358464], [96.115366, 31.370395], [96.112525, 31.37263], [96.093786, 31.371234], [96.091926, 31.372038], [96.080296, 31.385409], [96.079362, 31.385386], [96.066409, 31.377938], [96.065737, 31.378483], [96.059454, 31.388928], [96.059437, 31.389496], [96.062261, 31.398084], [96.061752, 31.400249], [96.057, 31.415923], [96.053649, 31.415572], [96.03491, 31.399763], [96.032742, 31.398382], [96.023789, 31.395889], [96.022764, 31.394966], [96.01308, 31.380197], [96.011718, 31.379485], [96.007136, 31.380386], [96.004519, 31.381897], [95.989827, 31.393659], [95.989911, 31.395801], [95.994845, 31.403398], [95.994455, 31.40447], [95.991112, 31.407576], [95.991456, 31.409379], [95.993023, 31.41747], [95.98393, 31.423351], [95.962682, 31.432462], [95.951429, 31.442996], [95.929911, 31.460612], [95.923762, 31.470824], [95.902128, 31.493512], [95.890283, 31.501099], [95.88075, 31.505433], [95.871645, 31.505631], [95.847306, 31.506631], [95.839879, 31.518718], [95.83068, 31.554001], [95.829988, 31.567998], [95.831295, 31.595937], [95.820208, 31.601684], [95.813128, 31.617199], [95.818304, 31.630151], [95.832291, 31.651155], [95.835632, 31.665516], [95.834473, 31.682637], [95.833451, 31.686237], [95.823801, 31.682496], [95.822096, 31.683407], [95.804958, 31.698657], [95.803252, 31.700806], [95.792628, 31.731059], [95.79152, 31.733094], [95.778709, 31.749773], [95.776803, 31.750741], [95.736183, 31.764115], [95.732616, 31.764519], [95.719616, 31.762968], [95.716576, 31.763705], [95.691626, 31.769655], [95.689453, 31.771123], [95.682802, 31.77637], [95.681211, 31.776313], [95.673925, 31.7726], [95.671291, 31.773616], [95.616548, 31.78375], [95.614699, 31.783358], [95.60587, 31.768894], [95.603882, 31.76805], [95.58147, 31.768442], [95.580274, 31.767204], [95.578575, 31.74884], [95.576868, 31.747433], [95.564591, 31.740206], [95.562945, 31.74021], [95.554936, 31.745985], [95.553611, 31.745595], [95.543995, 31.739433], [95.541365, 31.739783], [95.512917, 31.749143], [95.511672, 31.750556], [95.501011, 31.774101], [95.499299, 31.775121], [95.491751, 31.777574], [95.491094, 31.779099], [95.480146, 31.795713], [95.479091, 31.796221], [95.470346, 31.794846], [95.467249, 31.795984], [95.457124, 31.801654], [95.456008, 31.803741], [95.461097, 31.815896], [95.459591, 31.817648], [95.439904, 31.831681], [95.439965, 31.833799], [95.419331, 31.872239], [95.419392, 31.873246], [95.422184, 31.881918], [95.420797, 31.884006], [95.406416, 31.896924], [95.405696, 31.899404], [95.408291, 31.919349], [95.407042, 31.919631], [95.393423, 31.9202], [95.391903, 31.921553], [95.391669, 31.928097], [95.389359, 31.927488], [95.372504, 31.926483], [95.371748, 31.926823], [95.360935, 31.938088], [95.360604, 31.940049], [95.371445, 31.944993], [95.37154, 31.948577], [95.361126, 31.960485], [95.3619, 31.960799], [95.377268, 31.977802], [95.378928, 31.982659], [95.377877, 31.991979], [95.379476, 31.992939], [95.388996, 31.992715], [95.389665, 31.993279], [95.395648, 32.001451], [95.398713, 32.002031], [95.417488, 32.001294], [95.418095, 32.002293], [95.421772, 32.008198], [95.423809, 32.00814], [95.431471, 31.999265], [95.433152, 31.999512], [95.450456, 32.003228], [95.45211, 32.004331], [95.454438, 32.007849], [95.452396, 32.010266], [95.424391, 32.029671], [95.422561, 32.031896], [95.420533, 32.043796], [95.418313, 32.044594], [95.415295, 32.045954], [95.41559, 32.047097], [95.432122, 32.052413], [95.433127, 32.053711], [95.434141, 32.060928], [95.435389, 32.061269], [95.441937, 32.058467], [95.443479, 32.058577], [95.454699, 32.062516], [95.453929, 32.065098], [95.449687, 32.076922], [95.449852, 32.080931], [95.450537, 32.108573], [95.448026, 32.113373], [95.434073, 32.1225], [95.434134, 32.124392], [95.44135, 32.137688], [95.441212, 32.139407], [95.439393, 32.15892], [95.437713, 32.159836], [95.424749, 32.159561], [95.423267, 32.161161], [95.422079, 32.16768], [95.420649, 32.169281], [95.406442, 32.182154], [95.404776, 32.181125], [95.398188, 32.179148], [95.395687, 32.181196], [95.389053, 32.186085], [95.38604, 32.184402], [95.365349, 32.176677], [95.363679, 32.173339], [95.360384, 32.164484], [95.360506, 32.163955], [95.367043, 32.151653], [95.366991, 32.151395], [95.362836, 32.147529], [95.362574, 32.147442], [95.353697, 32.145978], [95.353549, 32.146056], [95.351453, 32.152039], [95.351184, 32.152264], [95.344374, 32.154828], [95.343808, 32.154822], [95.331639, 32.148941], [95.331369, 32.148932], [95.322236, 32.15249], [95.322062, 32.152479], [95.312859, 32.148873], [95.312815, 32.148914], [95.308032, 32.164005], [95.307893, 32.164087], [95.286573, 32.17158], [95.286355, 32.171773], [95.269949, 32.194632], [95.269923, 32.194763], [95.271521, 32.198913], [95.272864, 32.199294], [95.280871, 32.200866], [95.280351, 32.201799], [95.277387, 32.207525], [95.277178, 32.207636], [95.263791, 32.212054], [95.263696, 32.212263], [95.256055, 32.235497], [95.256038, 32.23566], [95.256455, 32.254316], [95.256342, 32.254601], [95.247046, 32.276775], [95.246655, 32.277421], [95.239869, 32.283258], [95.239818, 32.283443], [95.246404, 32.293553], [95.246395, 32.293972], [95.240738, 32.301924], [95.24072, 32.302087], [95.241024, 32.320509], [95.240799, 32.320534], [95.227346, 32.318258], [95.226938, 32.318317], [95.215208, 32.322576], [95.215069, 32.322461], [95.214583, 32.311049], [95.214514, 32.310885], [95.207997, 32.308465], [95.20791, 32.308285], [95.206324, 32.296409], [95.206099, 32.296273], [95.192019, 32.29342], [95.191811, 32.293241], [95.178082, 32.282134], [95.177891, 32.282082], [95.139176, 32.274256], [95.138907, 32.2741], [95.132389, 32.264003], [95.132164, 32.263999], [95.120693, 32.265129], [95.120398, 32.265027], [95.106482, 32.258886], [95.106335, 32.25894], [95.080256, 32.279028], [95.079987, 32.279345], [95.080309, 32.296883], [95.080718, 32.297606], [95.090787, 32.304949], [95.090813, 32.305029], [95.08607, 32.307789], [95.086105, 32.307874], [95.095737, 32.313502], [95.095772, 32.313572], [95.097076, 32.322301], [95.097828, 32.32238], [95.136683, 32.323916], [95.137354, 32.324221], [95.153977, 32.332428], [95.159322, 32.332245], [95.193525, 32.332303], [95.194193, 32.332793], [95.226667, 32.344812], [95.227257, 32.344945], [95.246879, 32.342709], [95.247319, 32.342993], [95.261711, 32.348086], [95.260017, 32.349537], [95.243368, 32.363582], [95.242943, 32.363745], [95.228804, 32.363119], [95.228726, 32.36331], [95.229263, 32.374185], [95.228917, 32.375244], [95.222838, 32.380182], [95.222743, 32.380454], [95.218495, 32.396891], [95.218356, 32.396948], [95.211596, 32.397753], [95.211544, 32.397679], [95.212896, 32.393317], [95.212714, 32.392925], [95.20728, 32.388088], [95.207046, 32.388091], [95.190974, 32.387038], [95.190696, 32.387093], [95.185776, 32.393691], [95.184105, 32.394186], [95.172966, 32.393541], [95.172827, 32.393491], [95.165378, 32.384545], [95.165066, 32.384573], [95.152895, 32.387313], [95.152835, 32.387554], [95.154646, 32.401724], [95.154576, 32.401733], [95.143495, 32.397363], [95.143105, 32.397323], [95.131223, 32.398882], [95.131092, 32.398845], [95.131075, 32.386473], [95.130719, 32.386354], [95.119942, 32.384852], [95.119812, 32.384881], [95.117279, 32.388264], [95.117019, 32.388229], [95.107172, 32.384228], [95.10639, 32.384281], [95.089634, 32.387932], [95.089426, 32.387873], [95.074975, 32.376045], [95.074784, 32.376091], [95.057008, 32.394765], [95.056643, 32.394975], [95.033462, 32.402909], [95.033262, 32.403041], [95.026983, 32.412087], [95.026939, 32.412092], [95.023899, 32.409503], [95.023551, 32.40933]]]]}}